hatecomp/__init__.py
hatecomp/_path.py
hatecomp/datasets/__init__.py
hatecomp/datasets/AMI/__init__.py
hatecomp/datasets/CONAN/__init__.py
hatecomp/datasets/Fox/__init__.py
hatecomp/datasets/HASOC/__init__.py
hatecomp/datasets/HASOC/dataset.py
hatecomp/datasets/HASOC/download.py
hatecomp/datasets/HateTwitter/__init__.py
hatecomp/datasets/MLMA/__init__.py
hatecomp/datasets/MLMA/dataset.py
hatecomp/datasets/MLMA/download.py
hatecomp/datasets/MultiTwitter/__init__.py
hatecomp/datasets/OnlineInter/__init__.py
hatecomp/datasets/TwitterSexism/__init__.py
hatecomp/datasets/TwitterSexism/dataset.py
hatecomp/datasets/TwitterSexism/download.py
hatecomp/datasets/UBWeb/__init__.py
hatecomp/datasets/UBWeb/Facebook/__init__.py
hatecomp/datasets/UBWeb/League/__init__.py
hatecomp/datasets/UBWeb/Twitter/__init__.py
hatecomp/datasets/UBWeb/WoW/__init__.py
hatecomp/datasets/Vicomtech/__init__.py
hatecomp/datasets/Vicomtech/dataset.py
hatecomp/datasets/Vicomtech/download.py
hatecomp/datasets/WikiTalk/__init__.py
hatecomp/datasets/WikiTalk/dataset.py
hatecomp/datasets/WikiTalk/download.py
hatecomp/datasets/ZeerakTalat/__init__.py
hatecomp/datasets/ZeerakTalat/dataset.py
hatecomp/datasets/ZeerakTalat/download.py
hatecomp/datasets/base/__init__.py
hatecomp/datasets/base/data.py
hatecomp/datasets/base/download.py
hatecomp/datasets/base/utils.py
hatecomp/models/__init__.py
hatecomp/models/auto.py
hatecomp/models/download.py
hatecomp/models/embed.py
hatecomp/models/model_registry.json
hatecomp/models/tokenizer.py
hatecomp/training/__init__.py
hatecomp/training/functional.py
hatecomp/training/hatecomp_trial.py
hatecomp/training/metrics.py
hatecomp/training/trainer.py
hatecomp/tweets/__init__.py
hatecomp/tweets/fetch.py
hatecomp-0.4.2.dist-info/METADATA
hatecomp-0.4.2.dist-info/WHEEL
hatecomp-0.4.2.dist-info/top_level.txt
hatecomp-0.4.2.dist-info/RECORD
