Metadata-Version: 2.1
Name: hatecomp
Version: 0.4.2
Summary: Collection of pytorch datasets for hate speech and toxic internet discourse
Home-page: https://github.com/HesitantlyHuman/hatecomp
Author: HesitantlyHuman
Author-email: tannersims@hesitantlyhuman.com
License: MIT
Requires-Dist: aiometer (<1.0.0,>=0.3.0)
Requires-Dist: httpx (<1.0.0,>=0.21.1)
Requires-Dist: requests (<3.0.0,>=2.0.0)
Requires-Dist: torch (<2.0.0,>=1.7.0)
Requires-Dist: tqdm (<5.0.0,>=4.1.0)
Requires-Dist: tweepy (<5.0.0,>=4.0.0)
Requires-Dist: transformers (<5.0.0,>=4.16.0)
